README.md
setup.py
aip/__init__.py
aip/base.py
aip/bodyanalysis.py
aip/easydl.py
aip/face.py
aip/imagecensor.py
aip/imageclassify.py
aip/imageprocess.py
aip/imagesearch.py
aip/kg.py
aip/nlp.py
aip/ocr.py
aip/speech.py
baidu_aip_http2.egg-info/PKG-INFO
baidu_aip_http2.egg-info/SOURCES.txt
baidu_aip_http2.egg-info/dependency_links.txt
baidu_aip_http2.egg-info/requires.txt
baidu_aip_http2.egg-info/top_level.txt
bin/aip_client