Metadata-Version: 1.0
Name: baidu-aip-http2
Version: 2.2.17.0
Summary: Baidu AIP SDK
Home-page: https://github.com/Baidu-AIP
Author: Baidu
Author-email: aip@baidu.com
License: Apache License
Keywords: baidu,aip,ocr,antiporn,nlp,face,kg,speech
Platform: UNKNOWN
